streamfitter/ExponentialDecay2Parameter.py
streamfitter/ExponentialDecay3Parameter.py
streamfitter/LinearLeastSquares.py
streamfitter/SymmetricExponentialPair.py
streamfitter/__init__.py
streamfitter/fitter.py
streamfitter/fitter_protocol.py
streamfitter/mean.py
streamfitter-0.1.9.dist-info/METADATA
streamfitter-0.1.9.dist-info/WHEEL
streamfitter-0.1.9.dist-info/licenses/LICENSE
streamfitter-0.1.9.dist-info/RECORD
