Metadata-Version: 2.3
Name: streamfitter
Version: 0.1.9
Summary: A program for fitting functions and calculating montecarlo based errors
Author-email: varioustoxins <garyt.and.sarahb@gmail.com>
Requires-Python: >=3.9
Requires-Dist: classprop>=0.1.1
Requires-Dist: jax>=0.4.28
Requires-Dist: jaxlib>=0.4.28
Requires-Dist: lmfit>=1.3.1
Requires-Dist: nef-pipelines
Requires-Dist: numpy>=1.26.4
Requires-Dist: pynmrstar==3.3.4
Requires-Dist: runstats>=2.0.0
Requires-Dist: tabulate==0.8.9
